ade/__init__.py
ade/__main__.py
ade/bloodhound/__init__.py
ade/bloodhound/__main__.py
ade/bloodhound/ad/__init__.py
ade/bloodhound/ad/authentication.py
ade/bloodhound/ad/computer.py
ade/bloodhound/ad/domain.py
ade/bloodhound/ad/structures.py
ade/bloodhound/ad/trusts.py
ade/bloodhound/ad/utils.py
ade/bloodhound/enumeration/__init__.py
ade/bloodhound/enumeration/acls.py
ade/bloodhound/enumeration/computers.py
ade/bloodhound/enumeration/domains.py
ade/bloodhound/enumeration/memberships.py
ade/bloodhound/enumeration/objectresolver.py
ade/bloodhound/enumeration/outputworker.py
ade/bloodhound/lib/__init__.py
ade/bloodhound/lib/cstruct.py
ade/connectors/__init__.py
ade/connectors/connectors.py
ade/cve_2020_1472/__init__.py
ade/cve_2020_1472/zerologon_tester.py
ade/exploits/__init__.py
ade/exploits/exploits.py
ade/external/LICENSE
ade/external/bloodhound/__init__.py
ade/external/bloodhound/__main__.py
ade/modEnumerator/__init__.py
ade/modEnumerator/modEnumerator.py
ActiveDirectoryEnum-0.5.0.dist-info/LICENSE
ActiveDirectoryEnum-0.5.0.dist-info/METADATA
ActiveDirectoryEnum-0.5.0.dist-info/WHEEL
ActiveDirectoryEnum-0.5.0.dist-info/top_level.txt
ActiveDirectoryEnum-0.5.0.dist-info/RECORD
