Metadata-Version: 2.1
Name: ActiveDirectoryEnum
Version: 0.5.0
Summary: Enumerate Active Directory with standard vectors
Home-page: https://github.com/CasperGN/ActiveDirectoryEnumeration
Author: Casper G. Nielsen
Author-email: whopsec@protonmail.com
License: UNKNOWN
Keywords: active-directory pentesting enumeration
Platform: UNKNOWN
Classifier: Programming Language :: Python :: 3
Classifier: License :: OSI Approved :: MIT License
Classifier: Environment :: Console
Requires-Python: >=3.4
Requires-Dist: cffi (==1.14.2)
Requires-Dist: Click (==7.1.2)
Requires-Dist: cryptography (==3.1)
Requires-Dist: dnspython (==1.16.0)
Requires-Dist: Flask (==1.1.2)
Requires-Dist: future (==0.18.2)
Requires-Dist: impacket (==0.9.21)
Requires-Dist: itsdangerous (==1.1.0)
Requires-Dist: Jinja2 (==2.11.2)
Requires-Dist: ldap3 (==2.8.1)
Requires-Dist: ldapdomaindump (==0.9.3)
Requires-Dist: MarkupSafe (==1.1.1)
Requires-Dist: progressbar (==2.5)
Requires-Dist: pyasn1 (==0.4.8)
Requires-Dist: pycparser (==2.20)
Requires-Dist: pycryptodomex (==3.9.8)
Requires-Dist: pyOpenSSL (==19.1.0)
Requires-Dist: six (==1.15.0)
Requires-Dist: termcolor (==1.1.0)
Requires-Dist: Werkzeug (==1.0.1)
Requires-Dist: bloodhound (==1.0.5)
